composabl_cli_dev-0.19.1.dist-info/METADATA
composabl_cli_dev-0.19.1.dist-info/entry_points.txt
composabl_cli_dev-0.19.1.dist-info/RECORD
composabl_cli_dev-0.19.1.dist-info/top_level.txt
composabl_cli_dev-0.19.1.dist-info/WHEEL
composabl_cli/__init__.py
composabl_cli/k8s/util.cpython-310-aarch64-linux-gnu.so
composabl_cli/k8s/k8s_train.cpython-310-aarch64-linux-gnu.so
composabl_cli/template/sim_docker/README.md
composabl_cli/template/sim_docker/Dockerfile
composabl_cli/template/sim_docker/main.py
composabl_cli/template/sim_docker/module/README.md
composabl_cli/template/sim_docker/module/pyproject.toml
composabl_cli/template/sim_docker/module/{{NAME_MODULE}}/sim.py
composabl_cli/template/sim_docker/module/{{NAME_MODULE}}/sim_impl.py
composabl_cli/template/sim_docker/module/{{NAME_MODULE}}/__init__.py
composabl_cli/template/sim_docker/docker/sim-start.sh
composabl_cli/template/skill_controller/README.md
composabl_cli/template/skill_controller/pyproject.toml
composabl_cli/template/skill_controller/{{NAME_MODULE}}/controller.py
composabl_cli/template/skill_controller/{{NAME_MODULE}}/__init__.py
composabl_cli/template/skill_coordinated_set/README.md
composabl_cli/template/skill_coordinated_set/pyproject.toml
composabl_cli/template/skill_coordinated_set/{{NAME_MODULE}}/coach.py
composabl_cli/template/skill_coordinated_set/{{NAME_MODULE}}/__init__.py
composabl_cli/template/skill_teacher/README.md
composabl_cli/template/skill_teacher/pyproject.toml
composabl_cli/template/skill_teacher/{{NAME_MODULE}}/teacher.py
composabl_cli/template/skill_teacher/{{NAME_MODULE}}/__init__.py
composabl_cli/template/perceptor/README.md
composabl_cli/template/perceptor/pyproject.toml
composabl_cli/template/perceptor/{{NAME_MODULE}}/perceptor.py
composabl_cli/template/perceptor/{{NAME_MODULE}}/__init__.py
composabl_cli/template/agent_local/agent.py
composabl_cli/template/selector_controller/README.md
composabl_cli/template/selector_controller/pyproject.toml
composabl_cli/template/selector_controller/{{NAME_MODULE}}/controller.py
composabl_cli/template/selector_controller/{{NAME_MODULE}}/__init__.py
composabl_cli/template/selector_teacher/README.md
