Metadata-Version: 2.4
Name: composabl-cli-dev
Version: 0.19.1
Summary: the Composabl CLI
Author-email: Hunter Park <hunter@composabl.io>
Requires-Python: >=3.10, <3.13
Requires-Dist: typer[all]==0.11.0
Requires-Dist: click<8.2.0
Requires-Dist: cython
Requires-Dist: docker
Requires-Dist: kubernetes
Requires-Dist: jinja2
Requires-Dist: composabl-core-dev>=0.19.1
Requires-Dist: composabl-train-dev>=0.19.1
Requires-Dist: composabl-api-dev>=0.19.1
Requires-Dist: ruff
Requires-Dist: simple-term-menu
Dynamic: description
Dynamic: description-content-type
Dynamic: requires-python
